MANIFEST.in
README.rst
pyproject.toml
setup.cfg
setup.py
whatsapp_call/__init__.py
whatsapp_call/admin.py
whatsapp_call/apps.py
whatsapp_call/models.py
whatsapp_call/tests.py
whatsapp_call/views.py
whatsapp_call/migrations/0001_initial.py
whatsapp_call/migrations/0002_whatsapp_draft.py
whatsapp_call/migrations/__init__.py
whatsapp_call/static/css/whatsapp_call.css
whatsapp_call/static/js/whatsapp_call.js
whatsapp_call/templates/whatsapp_call/whatsapp_call_btn.html
whatsapp_call/templatetags/__init__.py
whatsapp_call/templatetags/template_tags.py
whatsapp_widget.egg-info/PKG-INFO
whatsapp_widget.egg-info/SOURCES.txt
whatsapp_widget.egg-info/dependency_links.txt
whatsapp_widget.egg-info/top_level.txt