Metadata-Version: 2.1
Name: whatsapp-widget
Version: 0.1
Summary: A Django app to conduct whatsapp chat.
Home-page: https://github.com/faracode-net/whatsapp-widget
Author: MoriZoki
Author-email: morizoki.django@gmail.com
License: BSD-3-Clause  # Example license
Platform: UNKNOWN
Classifier: Environment :: Web Environment
Classifier: Framework :: Django
Classifier: Intended Audience :: Developers
Classifier: License :: OSI Approved :: BSD License
Classifier: Operating System :: OS Independent
Classifier: Programming Language :: Python
Classifier: Programming Language :: Python :: 3
Classifier: Programming Language :: Python :: 3 :: Only
Classifier: Programming Language :: Python :: 3.8
Classifier: Programming Language :: Python :: 3.9
Classifier: Topic :: Internet :: WWW/HTTP
Classifier: Topic :: Internet :: WWW/HTTP :: Dynamic Content
Requires-Python: >=3.8
